setup.py
django_multiplefilefield.egg-info/PKG-INFO
django_multiplefilefield.egg-info/SOURCES.txt
django_multiplefilefield.egg-info/dependency_links.txt
django_multiplefilefield.egg-info/not-zip-safe
django_multiplefilefield.egg-info/top_level.txt
multiplefilefield/__init__.py
multiplefilefield/fields.py
multiplefilefield/forms.py
multiplefilefield/widgets.py
multiplefilefield/locale/zh/LC_MESSAGES/django.po
multiplefilefield/tests/__init__.py
multiplefilefield/tests/settings.py
multiplefilefield/tests/test_multiple_file_input.py
multiplefilefield/tests/urls.py
multiplefilefield_example/__init__.py
multiplefilefield_example/admin.py
multiplefilefield_example/models.py
multiplefilefield_example/views.py
multiplefilefield_example/migrations/0001_initial.py
multiplefilefield_example/migrations/0002_multiplemultiplefilefieldmodel.py
multiplefilefield_example/migrations/0003_testmultiplefile.py
multiplefilefield_example/migrations/__init__.py